setup.py
myadipkgnik/__init__.py
myadipkgnik/calc.py
myadipkgnik.egg-info/PKG-INFO
myadipkgnik.egg-info/SOURCES.txt
myadipkgnik.egg-info/dependency_links.txt
myadipkgnik.egg-info/top_level.txt