Metadata-Version: 2.1
Name: myadipkgnik
Version: 0.0.1
Summary: ADI python package module
Author: Nikhil
Author-email: nikhilsubramani@yahoo.com
Classifier: Programming Language :: Python :: 3
Classifier: Operating System :: OS Independent
